glue_setuptools/__init__.py
glue_setuptools/gdist.py
glue_setuptools/gupload.py
glue_setuptools-0.4.dist-info/LICENSE
glue_setuptools-0.4.dist-info/METADATA
glue_setuptools-0.4.dist-info/WHEEL
glue_setuptools-0.4.dist-info/entry_points.txt
glue_setuptools-0.4.dist-info/top_level.txt
glue_setuptools-0.4.dist-info/RECORD
